[
  {
    "full_name": "PointCloudLibrary/pcl",
    "stargazers_count": 6386,
    "open_issues_count": 628,
    "forks_count": 3905
  },
  {
    "full_name": "bytedeco/javacpp-presets",
    "stargazers_count": 1843,
    "open_issues_count": 143,
    "forks_count": 578
  },
  {
    "full_name": "AFLplusplus/AFLplusplus",
    "stargazers_count": 1866,
    "open_issues_count": 23,
    "forks_count": 374
  },
  {
    "full_name": "tarantool/libslave",
    "stargazers_count": 9,
    "open_issues_count": 12,
    "forks_count": 3
  }
]