[
  {
    "full_name": "PointCloudLibrary/pcl",
    "stargazers_count": 6005,
    "open_issues_count": 659,
    "forks_count": 3767
  },
  {
    "full_name": "bytedeco/javacpp-presets",
    "stargazers_count": 1773,
    "open_issues_count": 139,
    "forks_count": 555
  },
  {
    "full_name": "AFLplusplus/AFLplusplus",
    "stargazers_count": 1358,
    "open_issues_count": 19,
    "forks_count": 297
  },
  {
    "full_name": "tarantool/libslave",
    "stargazers_count": 9,
    "open_issues_count": 12,
    "forks_count": 2
  }
]